<annotation>
	<folder>bottle</folder>
	<filename>000019a.jpg</filename>
	<path>D:\Desktop\大三下学期\工训大赛\训练集\pic\trashnew\train\bottle\000019a.jpg</path>
	<source>
		<database>Unknown</database>
	</source>
	<size>
		<width>768</width>
		<height>768</height>
		<depth>3</depth>
	</size>
	<segmented>0</segmented>
	<object>
		<name>bottle</name>
		<pose>Unspecified</pose>
		<truncated>0</truncated>
		<difficult>0</difficult>
		<bndbox>
			<xmin>86</xmin>
			<ymin>25</ymin>
			<xmax>691</xmax>
			<ymax>545</ymax>
		</bndbox>
	</object>
</annotation>
